cococrawler/__init__.py
cococrawler/crawler.py
cococrawler/data_source.py
cococrawler/items.py
cococrawler/piplines.py
cococrawler/command/__init__.py
cococrawler/command/cmd.py
cococrawler/config/__init__.py
cococrawler/exceptions/__init__.py
cococrawler/templates/__init__.py
cococrawler/templates/config.py
cococrawler/templates/crawler.py
cococrawler/templates/items.py
cococrawler/templates/pipelines.py
cococrawler/templates/sources.py
cococrawler-0.0.5.dist-info/DESCRIPTION.rst
cococrawler-0.0.5.dist-info/METADATA
cococrawler-0.0.5.dist-info/RECORD
cococrawler-0.0.5.dist-info/WHEEL
cococrawler-0.0.5.dist-info/entry_points.txt
cococrawler-0.0.5.dist-info/metadata.json
cococrawler-0.0.5.dist-info/top_level.txt
