Metadata-Version: 2.0
Name: cococrawler
Version: 0.0.5
Summary: A distributed network crawler framework
Home-page: https://github.com/yjxkwp/cococrawler
Author: kwp
Author-email: yjxkwp@foxmail.com
License: MIT
Keywords: distributed,crawler,spider
Platform: UNKNOWN
Classifier: Environment :: Web Environment
Classifier: Intended Audience :: Developers
Classifier: Operating System :: OS Independent
Classifier: Topic :: Text Processing :: Indexing
Classifier: Topic :: Utilities
Classifier: Topic :: Internet
Classifier: Topic :: Software Development :: Libraries :: Python Modules
Classifier: Programming Language :: Python
Classifier: Programming Language :: Python :: 2
Classifier: Programming Language :: Python :: 2.6
Classifier: Programming Language :: Python :: 2.7
Requires-Dist: Jinja2
Requires-Dist: pymongo
Requires-Dist: redis
Requires-Dist: requests
